{
  "Table": [
    {
      "rows": [
        [
          {
            "text": "Menge",
            "bbox": [
              868,
              1941,
              1162,
              2078
            ],
            "confidence": 0.9997346997261047
          },
          {
            "text": "Beschreibung",
            "bbox": [
              1497,
              1943,
              2016,
              2062
            ],
            "confidence": 0.9996300339698792
          },
          {
            "text": "Einzelpreis £",
            "bbox": [
              3025,
              1943,
              3522,
              2062
            ],
            "confidence": 0.989404022693634
          },
          {
            "text": "Summe £",
            "bbox": [
              4104,
              1966,
              4451,
              2046
            ],
            "confidence": 0.9893060922622681
          }
        ],
        [
          {
            "text": "29",
            "bbox": [
              886,
              2112,
              996,
              2222
            ],
            "confidence": 0.9999372959136963
          },
          {
            "text": "Lautsprecher",
            "bbox": [
              1490,
              2103,
              1943,
              2223
            ],
            "confidence": 0.9995737075805664
          },
          {
            "text": "555.28",
            "bbox": [
              3285,
              2112,
              3521,
              2222
            ],
            "confidence": 0.9998100399971008
          },
          {
            "text": "8072.89",
            "bbox": [
              4178,
              2112,
              4458,
              2214
            ],
            "confidence": 0.9999682307243347
          }
        ],
        [
          {
            "text": "76",
            "bbox": [
              886,
              2273,
              996,
              2375
            ],
            "confidence": 0.9997429847717285
          },
          {
            "text": "Telefon",
            "bbox": [
              1489,
              2263,
              1781,
              2385
            ],
            "confidence": 0.9983474612236023
          },
          {
            "text": "8072.89",
            "bbox": [
              3231,
              2256,
              3530,
              2377
            ],
            "confidence": 0.9999607801437378
          },
          {
            "text": "5387.59",
            "bbox": [
              4178,
              2280,
              4443,
              2361
            ],
            "confidence": 0.999937117099762
          }
        ],
        [
          {
            "text": "39",
            "bbox": [
              878,
              2426,
              989,
              2529
            ],
            "confidence": 0.9999463558197021
          },
          {
            "text": "Druckerpatrone",
            "bbox": [
              1497,
              2425,
              2031,
              2544
            ],
            "confidence": 0.9989825487136841
          },
          {
            "text": "4792.09",
            "bbox": [
              3255,
              2434,
              3521,
              2514
            ],
            "confidence": 0.9999471306800842
          },
          {
            "text": "2855.30",
            "bbox": [
              4178,
              2426,
              4458,
              2529
            ],
            "confidence": 0.999926745891571
          }
        ]
      ],
      "bbox": [
        868,
        1941,
        4458,
        2544
      ],
      "score": 0.9634
    },
    {
      "rows": [
        [
          {
            "text": "Zwischensumme in Euro",
            "bbox": [
              2679,
              3815,
              3521,
              3910
            ],
            "confidence": 0.9993463158607483
          },
          {
            "text": "6289.91",
            "bbox": [
              4178,
              3808,
              4451,
              3910
            ],
            "confidence": 0.9999741315841675
          }
        ],
        [
          {
            "text": "MwSt",
            "bbox": [
              3299,
              3968,
              3528,
              4071
            ],
            "confidence": 0.9989739656448364
          },
          {
            "text": "19 %",
            "bbox": [
              4266,
              3976,
              4451,
              4063
            ],
            "confidence": 0.9937433004379272
          }
        ],
        [
          {
            "text": "Versandkosten",
            "bbox": [
              3034,
              4129,
              3521,
              4210
            ],
            "confidence": 0.9995754957199097
          },
          {
            "text": "898.14 €",
            "bbox": [
              4163,
              4129,
              4451,
              4210
            ],
            "confidence": 0.9971905946731567
          }
        ]
      ],
      "bbox": [
        2679,
        3808,
        4451,
        4210
      ],
      "score": 0.9634
    }
  ],
  "Caption": [],
  "Footnote": [],
  "Formula": [],
  "List-item": [],
  "Page-footer": [],
  "Page-header": [],
  "Section-header": [
    {
      "rows": [
        [
          {
            "text": "Nerger OHG mbH",
            "bbox": [
              900,
              467,
              2193,
              622
            ],
            "confidence": 0.9983458518981934
          }
        ]
      ],
      "bbox": [
        900,
        467,
        2193,
        622
      ]
    },
    {
      "rows": [
        [
          {
            "text": "Lieferadresse",
            "bbox": [
              3358,
              957,
              3920,
              1068
            ],
            "confidence": 0.9956158399581909
          }
        ]
      ],
      "bbox": [
        3358,
        957,
        3920,
        1068
      ]
    }
  ],
  "Text": [
    {
      "rows": [
        [
          {
            "text": "E-Mail: katerinakoehler@hotmail.de",
            "bbox": [
              2104,
              6439,
              3270,
              6512
            ],
            "confidence": 0.9970564842224121
          }
        ],
        [
          {
            "text": "nternet: http://www.schaaf.net/",
            "bbox": [
              2111,
              6541,
              3211,
              6636
            ],
            "confidence": 0.9827927947044373
          }
        ]
      ],
      "bbox": [
        2104,
        6439,
        3270,
        6636
      ]
    },
    {
      "rows": [
        [
          {
            "text": "Lucie Davids",
            "bbox": [
              2089,
              1096,
              2524,
              1177
            ],
            "confidence": 0.9995335936546326
          }
        ],
        [
          {
            "text": "LindnerstraBe 33",
            "bbox": [
              2089,
              1191,
              2657,
              1279
            ],
            "confidence": 0.9819798469543457
          }
        ],
        [
          {
            "text": "14465 Nordhausen",
            "bbox": [
              2081,
              1272,
              2724,
              1367
            ],
            "confidence": 0.9953920245170593
          }
        ]
      ],
      "bbox": [
        2081,
        1096,
        2724,
        1367
      ]
    },
    {
      "rows": [
        [
          {
            "text": "Vielen Dank für lhre Bestellung!",
            "bbox": [
              3077,
              4735,
              4444,
              4846
            ],
            "confidence": 0.9632906913757324
          }
        ]
      ],
      "bbox": [
        3077,
        4735,
        4444,
        4846
      ]
    },
    {
      "rows": [
        [
          {
            "text": "Lieferadresse",
            "bbox": [
              3358,
              957,
              3920,
              1068
            ],
            "confidence": 0.9956158399581909
          }
        ],
        [
          {
            "text": "Wie Rechnungsadresse",
            "bbox": [
              3365,
              1081,
              4126,
              1192
            ],
            "confidence": 0.9888253211975098
          }
        ]
      ],
      "bbox": [
        3358,
        957,
        4126,
        1192
      ]
    },
    {
      "rows": [
        [
          {
            "text": "el: 0677192553",
            "bbox": [
              923,
              6431,
              1432,
              6512
            ],
            "confidence": 0.9997232556343079
          }
        ],
        [
          {
            "text": "Fax: +49(0)0906855298",
            "bbox": [
              893,
              6548,
              1675,
              6621
            ],
            "confidence": 0.9997140169143677
          }
        ]
      ],
      "bbox": [
        893,
        6431,
        1675,
        6621
      ]
    },
    {
      "rows": [
        [
          {
            "text": "Wie Rechnungsadresse",
            "bbox": [
              3365,
              1081,
              4126,
              1192
            ],
            "confidence": 0.9888253211975098
          }
        ]
      ],
      "bbox": [
        3365,
        1081,
        4126,
        1192
      ]
    },
    {
      "rows": [
        [
          {
            "text": "Dobesweg 95,90989 Zerbst",
            "bbox": [
              893,
              650,
              1823,
              753
            ],
            "confidence": 0.9862856864929199
          }
        ]
      ],
      "bbox": [
        893,
        650,
        1823,
        753
      ]
    }
  ],
  "Title": [],
  "unmatched": [
    {
      "text": "15.02.2025",
      "bbox": [
        908,
        965,
        1321,
        1067
      ],
      "confidence": 0.9998258352279663
    },
    {
      "text": "An",
      "bbox": [
        2070,
        962,
        2226,
        1070
      ],
      "confidence": 0.9901835918426514
    },
    {
      "text": "0",
      "bbox": [
        435,
        1279,
        620,
        1432
      ],
      "confidence": 0.5952433347702026
    },
    {
      "text": "Anweisungen",
      "bbox": [
        900,
        1579,
        1454,
        1659
      ],
      "confidence": 0.9988090395927429
    },
    {
      "text": "Rechnung",
      "bbox": [
        396,
        1729,
        704,
        3087
      ],
      "confidence": 0.9983065128326416
    },
    {
      "text": "Gesamtkosten 69.35 £ fallig am",
      "bbox": [
        2414,
        4283,
        3521,
        4378
      ],
      "confidence": 0.9928419589996338
    },
    {
      "text": "11.02.2025",
      "bbox": [
        3704,
        4274,
        4076,
        4372
      ],
      "confidence": 0.9999862909317017
    }
  ]
}