{
  "Table": [
    {
      "rows": [
        [
          {
            "text": "Ing. Irmengard Gunpf",
            "bbox": [
              2162,
              1205,
              2902,
              1316
            ],
            "confidence": 0.9992364048957825
          },
          {
            "text": "Wie Rechnungsadresse",
            "bbox": [
              3403,
              1199,
              4133,
              1294
            ],
            "confidence": 0.9997057914733887
          }
        ],
        [
          {
            "text": "Joachim-Rust-StraBe 38",
            "bbox": [
              2169,
              1293,
              2946,
              1411
            ],
            "confidence": 0.995690107345581
          }
        ]
      ],
      "bbox": [
        2162,
        1199,
        4133,
        1411
      ],
      "score": 0.9301
    },
    {
      "rows": [
        [
          {
            "text": "62",
            "bbox": [
              1048,
              2229,
              1151,
              2331
            ],
            "confidence": 0.9998942613601685
          },
          {
            "text": "Lampe",
            "bbox": [
              1550,
              2222,
              1794,
              2324
            ],
            "confidence": 0.9992060661315918
          }
        ],
        [
          {
            "text": "57",
            "bbox": [
              1033,
              2361,
              1166,
              2485
            ],
            "confidence": 0.9993044137954712
          },
          {
            "text": "Bahnticket",
            "bbox": [
              1556,
              2359,
              1898,
              2464
            ],
            "confidence": 0.9990667104721069
          }
        ]
      ],
      "bbox": [
        1033,
        2222,
        1898,
        2485
      ],
      "score": 0.9301
    }
  ],
  "Caption": [],
  "Footnote": [],
  "Formula": [],
  "List-item": [],
  "Page-footer": [],
  "Page-header": [],
  "Section-header": [
    {
      "rows": [
        [
          {
            "text": "Ritter Gorlitz KG",
            "bbox": [
              1040,
              642,
              2097,
              783
            ],
            "confidence": 0.9721949100494385
          }
        ]
      ],
      "bbox": [
        1040,
        642,
        2097,
        783
      ]
    }
  ],
  "Text": [
    {
      "rows": [
        [
          {
            "text": "E-Mail: vhein@gmail.com",
            "bbox": [
              2280,
              6328,
              3123,
              6447
            ],
            "confidence": 0.9894741177558899
          }
        ],
        [
          {
            "text": "Internet: http://hartmann.org/",
            "bbox": [
              2280,
              6445,
              3292,
              6556
            ],
            "confidence": 0.9961721897125244
          }
        ]
      ],
      "bbox": [
        2280,
        6328,
        3292,
        6556
      ]
    },
    {
      "rows": [
        [
          {
            "text": "Tel: +49(0)2886076032",
            "bbox": [
              1136,
              6357,
              1883,
              6476
            ],
            "confidence": 0.9994441270828247
          }
        ],
        [
          {
            "text": "Fax: +49(0)5150 79567",
            "bbox": [
              1136,
              6467,
              1891,
              6593
            ],
            "confidence": 0.995080828666687
          }
        ]
      ],
      "bbox": [
        1136,
        6357,
        1891,
        6593
      ]
    },
    {
      "rows": [
        [
          {
            "text": "Vielen Dank für lhre Bestellung!",
            "bbox": [
              3188,
              4713,
              4510,
              4831
            ],
            "confidence": 0.9672213792800903
          }
        ]
      ],
      "bbox": [
        3188,
        4713,
        4510,
        4831
      ]
    },
    {
      "rows": [
        [
          {
            "text": "Ing. Irmengard Gunpf",
            "bbox": [
              2162,
              1205,
              2902,
              1316
            ],
            "confidence": 0.9992364048957825
          }
        ],
        [
          {
            "text": "Joachim-Rust-StraBe 38",
            "bbox": [
              2169,
              1293,
              2946,
              1411
            ],
            "confidence": 0.995690107345581
          }
        ],
        [
          {
            "text": " 07124 Finsterwalde",
            "bbox": [
              2169,
              1388,
              2798,
              1499
            ],
            "confidence": 0.9851953387260437
          }
        ]
      ],
      "bbox": [
        2162,
        1205,
        2946,
        1499
      ]
    },
    {
      "rows": [
        [
          {
            "text": "Internet: http://hartmann.org/",
            "bbox": [
              2280,
              6445,
              3292,
              6556
            ],
            "confidence": 0.9961721897125244
          }
        ]
      ],
      "bbox": [
        2280,
        6445,
        3292,
        6556
      ]
    },
    {
      "rows": [
        [
          {
            "text": "Wie Rechnungsadresse",
            "bbox": [
              3403,
              1199,
              4133,
              1294
            ],
            "confidence": 0.9997057914733887
          }
        ]
      ],
      "bbox": [
        3403,
        1199,
        4133,
        1294
      ]
    },
    {
      "rows": [
        [
          {
            "text": "E-Mail: vhein@gmail.com",
            "bbox": [
              2280,
              6328,
              3123,
              6447
            ],
            "confidence": 0.9894741177558899
          }
        ]
      ],
      "bbox": [
        2280,
        6328,
        3123,
        6447
      ]
    }
  ],
  "Title": [],
  "unmatched": [
    {
      "text": "Löfflerstr. 845, 89784 Schmölln",
      "bbox": [
        1025,
        811,
        2023,
        921
      ],
      "confidence": 0.9805123805999756
    },
    {
      "text": "Lieferadresse",
      "bbox": [
        3401,
        1073,
        3928,
        1192
      ],
      "confidence": 0.9770416617393494
    },
    {
      "text": " 84780",
      "bbox": [
        576,
        1118,
        819,
        1798
      ],
      "confidence": 0.9330961108207703
    },
    {
      "text": "An",
      "bbox": [
        2177,
        1111,
        2310,
        1199
      ],
      "confidence": 0.9923514127731323
    },
    {
      "text": "02.02.2025",
      "bbox": [
        1041,
        1133,
        1447,
        1213
      ],
      "confidence": 0.9999713897705078
    },
    {
      "text": "Rechnung &",
      "bbox": [
        589,
        1672,
        880,
        3064
      ],
      "confidence": 0.9641441106796265
    },
    {
      "text": "Anweisungen",
      "bbox": [
        1055,
        1717,
        1580,
        1798
      ],
      "confidence": 0.9992267489433289
    },
    {
      "text": "summe",
      "bbox": [
        4148,
        2024,
        4473,
        2127
      ],
      "confidence": 0.9920647740364075
    },
    {
      "text": "Einzelpreis",
      "bbox": [
        3144,
        2039,
        3565,
        2141
      ],
      "confidence": 0.9982055425643921
    },
    {
      "text": "Beschreibung",
      "bbox": [
        1542,
        2068,
        2104,
        2178
      ],
      "confidence": 0.9983575344085693
    },
    {
      "text": "Menge",
      "bbox": [
        1019,
        2083,
        1351,
        2185
      ],
      "confidence": 0.9983294606208801
    },
    {
      "text": "150.98 €",
      "bbox": [
        4170,
        2163,
        4465,
        2266
      ],
      "confidence": 0.9756802320480347
    },
    {
      "text": "392.03 €",
      "bbox": [
        3277,
        2178,
        3580,
        2280
      ],
      "confidence": 0.9956214427947998
    },
    {
      "text": "150.98 €",
      "bbox": [
        3285,
        2324,
        3580,
        2426
      ],
      "confidence": 0.9825323820114136
    },
    {
      "text": "304.42 €",
      "bbox": [
        4178,
        2317,
        4473,
        2419
      ],
      "confidence": 0.9952195882797241
    },
    {
      "text": "96.89 €",
      "bbox": [
        3321,
        2478,
        3587,
        2580
      ],
      "confidence": 0.9845849275588989
    },
    {
      "text": "129.13 €",
      "bbox": [
        4185,
        2470,
        4465,
        2551
      ],
      "confidence": 0.9983617067337036
    },
    {
      "text": "22",
      "bbox": [
        1048,
        2521,
        1159,
        2624
      ],
      "confidence": 0.999930202960968
    },
    {
      "text": "Adapter",
      "bbox": [
        1565,
        2529,
        1830,
        2609
      ],
      "confidence": 0.9998623132705688
    },
    {
      "text": "282.56 €",
      "bbox": [
        4207,
        3808,
        4510,
        3888
      ],
      "confidence": 0.9981659650802612
    },
    {
      "text": "Zwischensumme",
      "bbox": [
        3055,
        3829,
        3595,
        3918
      ],
      "confidence": 0.9993371963500977
    },
    {
      "text": "19 %",
      "bbox": [
        4318,
        3954,
        4502,
        4042
      ],
      "confidence": 0.961799144744873
    },
    {
      "text": "MwSt",
      "bbox": [
        3388,
        3968,
        3617,
        4071
      ],
      "confidence": 0.9718048572540283
    },
    {
      "text": "392.03 €",
      "bbox": [
        4207,
        4093,
        4510,
        4195
      ],
      "confidence": 0.9961926937103271
    },
    {
      "text": "Versandkosten",
      "bbox": [
        3130,
        4129,
        3595,
        4210
      ],
      "confidence": 0.9996740818023682
    },
    {
      "text": "25.05.2025",
      "bbox": [
        4126,
        4246,
        4495,
        4327
      ],
      "confidence": 0.9999756813049316
    },
    {
      "text": "Gesamtkosten fallig am",
      "bbox": [
        2789,
        4260,
        3603,
        4371
      ],
      "confidence": 0.9832877516746521
    }
  ]
}